MANIFEST.in
README.md
setup.cfg
setup.py
bikesanity/__init__.py
bikesanity/run.py
bikesanity.egg-info/PKG-INFO
bikesanity.egg-info/SOURCES.txt
bikesanity.egg-info/dependency_links.txt
bikesanity.egg-info/entry_points.txt
bikesanity.egg-info/requires.txt
bikesanity.egg-info/top_level.txt
bikesanity/entities/__init__.py
bikesanity/entities/content_blocks.py
bikesanity/entities/journal.py
bikesanity/entities/page.py
bikesanity/entities/json/__init__.py
bikesanity/entities/json/journal.py
bikesanity/interpreter/__init__.py
bikesanity/interpreter/interpreter_base.py
bikesanity/interpreter/journal_content.py
bikesanity/interpreter/page_interpreter.py
bikesanity/io_utils/__init__.py
bikesanity/io_utils/base_session.py
bikesanity/io_utils/custom_retry.py
bikesanity/io_utils/file_handler.py
bikesanity/io_utils/local_journal.py
bikesanity/io_utils/log_handler.py
bikesanity/io_utils/plain_session.py
bikesanity/io_utils/resources.py
bikesanity/io_utils/serializer.py
bikesanity/io_utils/throttled.py
bikesanity/io_utils/timeout_http_adaptor.py
bikesanity/output_transformers/__init__.py
bikesanity/output_transformers/disk_html_output.py
bikesanity/output_transformers/json_output.py
bikesanity/output_transformers/pdf_output.py
bikesanity/output_transformers/templated_html_output.py
bikesanity/output_transformers/pdf_templates/__init__.py
bikesanity/output_transformers/pdf_templates/base_pdf_template.py
bikesanity/output_transformers/pdf_templates/journal_pdf.py
bikesanity/output_transformers/pdf_templates/journal_pdf_reduced.py
bikesanity/processing/__init__.py
bikesanity/processing/download_journal.py
bikesanity/processing/load_disk_journal.py
bikesanity/processing/publish_journal.py
bikesanity/resources/serialized.pickle
bikesanity/resources/fonts/DejaVuSans-Bold.ttf
bikesanity/resources/fonts/DejaVuSans-Oblique.ttf
bikesanity/resources/fonts/DejaVuSans.ttf
bikesanity/resources/fonts/LICENSE
bikesanity/resources/templates/index.html
bikesanity/resources/templates/page.html
bikesanity/resources/templates/css/fontawesome-all.min.css
bikesanity/resources/templates/css/journal.css
bikesanity/resources/templates/css/responsive.css
bikesanity/resources/templates/css/images/dark-bl.svg
