Metadata-Version: 2.1
Name: bikesanity
Version: 1.1.6
Summary: BikeSanity cycle touring journal extractor and formatter
Home-page: https://github.com/JohnHenrySplitMyHeart/bikesanity
Author: John Henry
Author-email: john.henry.split.my.heart@protonmail.com
License: UNKNOWN
Download-URL: https://github.com/JohnHenrySplitMyHeart/bikesanity/archive/v_1.1.6.tar.gz
Platform: UNKNOWN
Classifier: Programming Language :: Python :: 3
Classifier: License :: OSI Approved :: Apache Software License
Classifier: Operating System :: OS Independent
Requires-Python: >=3.6
